<art:details xmlns:udf="http://genologics.com/ri/userdefined" xmlns:file="http://genologics.com/ri/file" xmlns:art="http://genologics.com/ri/artifact">
    <art:artifact uri="http://web-claritytest-01.internal.sanger.ac.uk:8080/api/v2/artifacts/92-411045?state=210373" limsid="92-411045">
        <name>Plate 1</name>
        <type>ResultFile</type>
        <output-type>ResultFile</output-type>
        <parent-process uri="http://web-claritytest-01.internal.sanger.ac.uk:8080/api/v2/processes/24-68287" limsid="24-68287"/>
        <qc-flag>UNKNOWN</qc-flag>
        <sample uri="http://web-claritytest-01.internal.sanger.ac.uk:8080/api/v2/samples/44Y203A81" limsid="44Y203A81"/>
        <sample uri="http://web-claritytest-01.internal.sanger.ac.uk:8080/api/v2/samples/44Y203A73" limsid="44Y203A73"/>
        <sample uri="http://web-claritytest-01.internal.sanger.ac.uk:8080/api/v2/samples/44Y203A72" limsid="44Y203A72"/>
        <sample uri="http://web-claritytest-01.internal.sanger.ac.uk:8080/api/v2/samples/44Y203A75" limsid="44Y203A75"/>
        <sample uri="http://web-claritytest-01.internal.sanger.ac.uk:8080/api/v2/samples/44Y203A74" limsid="44Y203A74"/>
        <sample uri="http://web-claritytest-01.internal.sanger.ac.uk:8080/api/v2/samples/44Y203A77" limsid="44Y203A77"/>
        <sample uri="http://web-claritytest-01.internal.sanger.ac.uk:8080/api/v2/samples/44Y203A76" limsid="44Y203A76"/>
        <sample uri="http://web-claritytest-01.internal.sanger.ac.uk:8080/api/v2/samples/44Y203A79" limsid="44Y203A79"/>
        <sample uri="http://web-claritytest-01.internal.sanger.ac.uk:8080/api/v2/samples/44Y203A78" limsid="44Y203A78"/>
        <sample uri="http://web-claritytest-01.internal.sanger.ac.uk:8080/api/v2/samples/44Y203A5" limsid="44Y203A5"/>
        <sample uri="http://web-claritytest-01.internal.sanger.ac.uk:8080/api/v2/samples/44Y203A4" limsid="44Y203A4"/>
        <sample uri="http://web-claritytest-01.internal.sanger.ac.uk:8080/api/v2/samples/44Y203A7" limsid="44Y203A7"/>
        <sample uri="http://web-claritytest-01.internal.sanger.ac.uk:8080/api/v2/samples/44Y203A6" limsid="44Y203A6"/>
        <sample uri="http://web-claritytest-01.internal.sanger.ac.uk:8080/api/v2/samples/44Y203A16" limsid="44Y203A16"/>
        <sample uri="http://web-claritytest-01.internal.sanger.ac.uk:8080/api/v2/samples/44Y203A8" limsid="44Y203A8"/>
        <sample uri="http://web-claritytest-01.internal.sanger.ac.uk:8080/api/v2/samples/44Y203A9" limsid="44Y203A9"/>
        <sample uri="http://web-claritytest-01.internal.sanger.ac.uk:8080/api/v2/samples/44Y203A10" limsid="44Y203A10"/>
        <sample uri="http://web-claritytest-01.internal.sanger.ac.uk:8080/api/v2/samples/44Y203A11" limsid="44Y203A11"/>
        <sample uri="http://web-claritytest-01.internal.sanger.ac.uk:8080/api/v2/samples/44Y203A12" limsid="44Y203A12"/>
        <sample uri="http://web-claritytest-01.internal.sanger.ac.uk:8080/api/v2/samples/44Y203A13" limsid="44Y203A13"/>
        <sample uri="http://web-claritytest-01.internal.sanger.ac.uk:8080/api/v2/samples/44Y203A14" limsid="44Y203A14"/>
        <sample uri="http://web-claritytest-01.internal.sanger.ac.uk:8080/api/v2/samples/44Y203A15" limsid="44Y203A15"/>
        <sample uri="http://web-claritytest-01.internal.sanger.ac.uk:8080/api/v2/samples/44Y203A87" limsid="44Y203A87"/>
        <sample uri="http://web-claritytest-01.internal.sanger.ac.uk:8080/api/v2/samples/44Y203A86" limsid="44Y203A86"/>
        <sample uri="http://web-claritytest-01.internal.sanger.ac.uk:8080/api/v2/samples/44Y203A85" limsid="44Y203A85"/>
        <sample uri="http://web-claritytest-01.internal.sanger.ac.uk:8080/api/v2/samples/44Y203A84" limsid="44Y203A84"/>
        <sample uri="http://web-claritytest-01.internal.sanger.ac.uk:8080/api/v2/samples/44Y203A17" limsid="44Y203A17"/>
        <sample uri="http://web-claritytest-01.internal.sanger.ac.uk:8080/api/v2/samples/44Y203A19" limsid="44Y203A19"/>
        <sample uri="http://web-claritytest-01.internal.sanger.ac.uk:8080/api/v2/samples/44Y203A18" limsid="44Y203A18"/>
        <sample uri="http://web-claritytest-01.internal.sanger.ac.uk:8080/api/v2/samples/44Y203A39" limsid="44Y203A39"/>
        <sample uri="http://web-claritytest-01.internal.sanger.ac.uk:8080/api/v2/samples/44Y203A38" limsid="44Y203A38"/>
        <sample uri="http://web-claritytest-01.internal.sanger.ac.uk:8080/api/v2/samples/44Y203A37" limsid="44Y203A37"/>
        <sample uri="http://web-claritytest-01.internal.sanger.ac.uk:8080/api/v2/samples/44Y203A36" limsid="44Y203A36"/>
        <sample uri="http://web-claritytest-01.internal.sanger.ac.uk:8080/api/v2/samples/44Y203A43" limsid="44Y203A43"/>
        <sample uri="http://web-claritytest-01.internal.sanger.ac.uk:8080/api/v2/samples/44Y203A42" limsid="44Y203A42"/>
        <sample uri="http://web-claritytest-01.internal.sanger.ac.uk:8080/api/v2/samples/44Y203A41" limsid="44Y203A41"/>
        <sample uri="http://web-claritytest-01.internal.sanger.ac.uk:8080/api/v2/samples/44Y203A47" limsid="44Y203A47"/>
        <sample uri="http://web-claritytest-01.internal.sanger.ac.uk:8080/api/v2/samples/44Y203A46" limsid="44Y203A46"/>
        <sample uri="http://web-claritytest-01.internal.sanger.ac.uk:8080/api/v2/samples/44Y203A44" limsid="44Y203A44"/>
        <sample uri="http://web-claritytest-01.internal.sanger.ac.uk:8080/api/v2/samples/44Y203A51" limsid="44Y203A51"/>
        <sample uri="http://web-claritytest-01.internal.sanger.ac.uk:8080/api/v2/samples/44Y203A50" limsid="44Y203A50"/>
        <sample uri="http://web-claritytest-01.internal.sanger.ac.uk:8080/api/v2/samples/44Y203A49" limsid="44Y203A49"/>
        <sample uri="http://web-claritytest-01.internal.sanger.ac.uk:8080/api/v2/samples/44Y203A48" limsid="44Y203A48"/>
        <sample uri="http://web-claritytest-01.internal.sanger.ac.uk:8080/api/v2/samples/44Y203A22" limsid="44Y203A22"/>
        <sample uri="http://web-claritytest-01.internal.sanger.ac.uk:8080/api/v2/samples/44Y203A23" limsid="44Y203A23"/>
        <sample uri="http://web-claritytest-01.internal.sanger.ac.uk:8080/api/v2/samples/44Y203A20" limsid="44Y203A20"/>
        <sample uri="http://web-claritytest-01.internal.sanger.ac.uk:8080/api/v2/samples/44Y203A21" limsid="44Y203A21"/>
        <sample uri="http://web-claritytest-01.internal.sanger.ac.uk:8080/api/v2/samples/44Y203A26" limsid="44Y203A26"/>
        <sample uri="http://web-claritytest-01.internal.sanger.ac.uk:8080/api/v2/samples/44Y203A27" limsid="44Y203A27"/>
        <sample uri="http://web-claritytest-01.internal.sanger.ac.uk:8080/api/v2/samples/44Y203A24" limsid="44Y203A24"/>
        <sample uri="http://web-claritytest-01.internal.sanger.ac.uk:8080/api/v2/samples/44Y203A25" limsid="44Y203A25"/>
        <sample uri="http://web-claritytest-01.internal.sanger.ac.uk:8080/api/v2/samples/44Y203A30" limsid="44Y203A30"/>
        <sample uri="http://web-claritytest-01.internal.sanger.ac.uk:8080/api/v2/samples/44Y203A31" limsid="44Y203A31"/>
        <sample uri="http://web-claritytest-01.internal.sanger.ac.uk:8080/api/v2/samples/44Y203A28" limsid="44Y203A28"/>
        <sample uri="http://web-claritytest-01.internal.sanger.ac.uk:8080/api/v2/samples/44Y203A29" limsid="44Y203A29"/>
        <sample uri="http://web-claritytest-01.internal.sanger.ac.uk:8080/api/v2/samples/44Y203A34" limsid="44Y203A34"/>
        <sample uri="http://web-claritytest-01.internal.sanger.ac.uk:8080/api/v2/samples/44Y203A35" limsid="44Y203A35"/>
        <sample uri="http://web-claritytest-01.internal.sanger.ac.uk:8080/api/v2/samples/44Y203A32" limsid="44Y203A32"/>
        <sample uri="http://web-claritytest-01.internal.sanger.ac.uk:8080/api/v2/samples/44Y203A33" limsid="44Y203A33"/>
        <sample uri="http://web-claritytest-01.internal.sanger.ac.uk:8080/api/v2/samples/44Y203A69" limsid="44Y203A69"/>
        <sample uri="http://web-claritytest-01.internal.sanger.ac.uk:8080/api/v2/samples/44Y203A68" limsid="44Y203A68"/>
        <sample uri="http://web-claritytest-01.internal.sanger.ac.uk:8080/api/v2/samples/44Y203A71" limsid="44Y203A71"/>
        <sample uri="http://web-claritytest-01.internal.sanger.ac.uk:8080/api/v2/samples/44Y203A70" limsid="44Y203A70"/>
        <sample uri="http://web-claritytest-01.internal.sanger.ac.uk:8080/api/v2/samples/3C-153" limsid="3C-153"/>
        <sample uri="http://web-claritytest-01.internal.sanger.ac.uk:8080/api/v2/samples/44Y203A80" limsid="44Y203A80"/>
        <sample uri="http://web-claritytest-01.internal.sanger.ac.uk:8080/api/v2/samples/44Y203A83" limsid="44Y203A83"/>
        <sample uri="http://web-claritytest-01.internal.sanger.ac.uk:8080/api/v2/samples/44Y203A82" limsid="44Y203A82"/>
        <sample uri="http://web-claritytest-01.internal.sanger.ac.uk:8080/api/v2/samples/44Y203A52" limsid="44Y203A52"/>
        <sample uri="http://web-claritytest-01.internal.sanger.ac.uk:8080/api/v2/samples/44Y203A53" limsid="44Y203A53"/>
        <sample uri="http://web-claritytest-01.internal.sanger.ac.uk:8080/api/v2/samples/44Y203A54" limsid="44Y203A54"/>
        <sample uri="http://web-claritytest-01.internal.sanger.ac.uk:8080/api/v2/samples/44Y203A55" limsid="44Y203A55"/>
        <sample uri="http://web-claritytest-01.internal.sanger.ac.uk:8080/api/v2/samples/44Y203A56" limsid="44Y203A56"/>
        <sample uri="http://web-claritytest-01.internal.sanger.ac.uk:8080/api/v2/samples/44Y203A57" limsid="44Y203A57"/>
        <sample uri="http://web-claritytest-01.internal.sanger.ac.uk:8080/api/v2/samples/44Y203A58" limsid="44Y203A58"/>
        <sample uri="http://web-claritytest-01.internal.sanger.ac.uk:8080/api/v2/samples/44Y203A59" limsid="44Y203A59"/>
        <sample uri="http://web-claritytest-01.internal.sanger.ac.uk:8080/api/v2/samples/44Y203A60" limsid="44Y203A60"/>
        <sample uri="http://web-claritytest-01.internal.sanger.ac.uk:8080/api/v2/samples/44Y203A61" limsid="44Y203A61"/>
        <sample uri="http://web-claritytest-01.internal.sanger.ac.uk:8080/api/v2/samples/44Y203A62" limsid="44Y203A62"/>
        <sample uri="http://web-claritytest-01.internal.sanger.ac.uk:8080/api/v2/samples/44Y203A63" limsid="44Y203A63"/>
        <sample uri="http://web-claritytest-01.internal.sanger.ac.uk:8080/api/v2/samples/44Y203A64" limsid="44Y203A64"/>
        <sample uri="http://web-claritytest-01.internal.sanger.ac.uk:8080/api/v2/samples/44Y203A65" limsid="44Y203A65"/>
        <sample uri="http://web-claritytest-01.internal.sanger.ac.uk:8080/api/v2/samples/44Y203A66" limsid="44Y203A66"/>
        <sample uri="http://web-claritytest-01.internal.sanger.ac.uk:8080/api/v2/samples/3C-405" limsid="3C-405"/>
        <sample uri="http://web-claritytest-01.internal.sanger.ac.uk:8080/api/v2/samples/3C-402" limsid="3C-402"/>
        <sample uri="http://web-claritytest-01.internal.sanger.ac.uk:8080/api/v2/samples/3C-452" limsid="3C-452"/>
        <sample uri="http://web-claritytest-01.internal.sanger.ac.uk:8080/api/v2/samples/2C-464" limsid="2C-464"/>
        <control-type uri="http://web-claritytest-01.internal.sanger.ac.uk:8080/api/v2/controltypes/2"/>
        <workflow-stages/>
    </art:artifact>
    <art:artifact uri="http://web-claritytest-01.internal.sanger.ac.uk:8080/api/v2/artifacts/2-411046?state=210374" limsid="2-411046">
        <name>Fluidigm Analysis File</name>
        <type>Analyte</type>
        <output-type>Analyte</output-type>
        <parent-process uri="http://web-claritytest-01.internal.sanger.ac.uk:8080/api/v2/processes/24-68287" limsid="24-68287"/>
        <qc-flag>UNKNOWN</qc-flag>
        <location>
            <container uri="http://web-claritytest-01.internal.sanger.ac.uk:8080/api/v2/containers/27-14426" limsid="27-14426"/>
            <value>K:1</value>
        </location>
        <working-flag>true</working-flag>
        <sample uri="http://web-claritytest-01.internal.sanger.ac.uk:8080/api/v2/samples/3C-153" limsid="3C-153"/>
        <control-type uri="http://web-claritytest-01.internal.sanger.ac.uk:8080/api/v2/controltypes/3"/>
        <workflow-stages/>
    </art:artifact>
    <art:artifact uri="http://web-claritytest-01.internal.sanger.ac.uk:8080/api/v2/artifacts/2-411047?state=210375" limsid="2-411047">
        <name>Fluidigm Analysis File</name>
        <type>Analyte</type>
        <output-type>Analyte</output-type>
        <parent-process uri="http://web-claritytest-01.internal.sanger.ac.uk:8080/api/v2/processes/24-68287" limsid="24-68287"/>
        <qc-flag>UNKNOWN</qc-flag>
        <location>
            <container uri="http://web-claritytest-01.internal.sanger.ac.uk:8080/api/v2/containers/27-14426" limsid="27-14426"/>
            <value>H:4</value>
        </location>
        <working-flag>true</working-flag>
        <sample uri="http://web-claritytest-01.internal.sanger.ac.uk:8080/api/v2/samples/44Y203A16" limsid="44Y203A16"/>
        <workflow-stages/>
    </art:artifact>
    <art:artifact uri="http://web-claritytest-01.internal.sanger.ac.uk:8080/api/v2/artifacts/2-411048?state=210376" limsid="2-411048">
        <name>Fluidigm Analysis File</name>
        <type>Analyte</type>
        <output-type>Analyte</output-type>
        <parent-process uri="http://web-claritytest-01.internal.sanger.ac.uk:8080/api/v2/processes/24-68287" limsid="24-68287"/>
        <qc-flag>UNKNOWN</qc-flag>
        <location>
            <container uri="http://web-claritytest-01.internal.sanger.ac.uk:8080/api/v2/containers/27-14426" limsid="27-14426"/>
            <value>D:2</value>
        </location>
        <working-flag>true</working-flag>
        <sample uri="http://web-claritytest-01.internal.sanger.ac.uk:8080/api/v2/samples/44Y203A10" limsid="44Y203A10"/>
        <workflow-stages/>
    </art:artifact>
    <art:artifact uri="http://web-claritytest-01.internal.sanger.ac.uk:8080/api/v2/artifacts/2-411049?state=210377" limsid="2-411049">
        <name>Fluidigm Analysis File</name>
        <type>Analyte</type>
        <output-type>Analyte</output-type>
        <parent-process uri="http://web-claritytest-01.internal.sanger.ac.uk:8080/api/v2/processes/24-68287" limsid="24-68287"/>
        <qc-flag>UNKNOWN</qc-flag>
        <location>
            <container uri="http://web-claritytest-01.internal.sanger.ac.uk:8080/api/v2/containers/27-14426" limsid="27-14426"/>
            <value>E:3</value>
        </location>
        <working-flag>true</working-flag>
        <sample uri="http://web-claritytest-01.internal.sanger.ac.uk:8080/api/v2/samples/44Y203A11" limsid="44Y203A11"/>
        <workflow-stages/>
    </art:artifact>
    <art:artifact uri="http://web-claritytest-01.internal.sanger.ac.uk:8080/api/v2/artifacts/2-411050?state=210378" limsid="2-411050">
        <name>Fluidigm Analysis File</name>
        <type>Analyte</type>
        <output-type>Analyte</output-type>
        <parent-process uri="http://web-claritytest-01.internal.sanger.ac.uk:8080/api/v2/processes/24-68287" limsid="24-68287"/>
        <qc-flag>UNKNOWN</qc-flag>
        <location>
            <container uri="http://web-claritytest-01.internal.sanger.ac.uk:8080/api/v2/containers/27-14426" limsid="27-14426"/>
            <value>G:1</value>
        </location>
        <working-flag>true</working-flag>
        <sample uri="http://web-claritytest-01.internal.sanger.ac.uk:8080/api/v2/samples/44Y203A8" limsid="44Y203A8"/>
        <workflow-stages/>
    </art:artifact>
    <art:artifact uri="http://web-claritytest-01.internal.sanger.ac.uk:8080/api/v2/artifacts/2-411101?state=210379" limsid="2-411101">
        <name>Fluidigm Analysis File</name>
        <type>Analyte</type>
        <output-type>Analyte</output-type>
        <parent-process uri="http://web-claritytest-01.internal.sanger.ac.uk:8080/api/v2/processes/24-68287" limsid="24-68287"/>
        <qc-flag>UNKNOWN</qc-flag>
        <location>
            <container uri="http://web-claritytest-01.internal.sanger.ac.uk:8080/api/v2/containers/27-14426" limsid="27-14426"/>
            <value>B:1</value>
        </location>
        <working-flag>true</working-flag>
        <sample uri="http://web-claritytest-01.internal.sanger.ac.uk:8080/api/v2/samples/44Y203A9" limsid="44Y203A9"/>
        <workflow-stages/>
    </art:artifact>
    <art:artifact uri="http://web-claritytest-01.internal.sanger.ac.uk:8080/api/v2/artifacts/2-411102?state=210380" limsid="2-411102">
        <name>Fluidigm Analysis File</name>
        <type>Analyte</type>
        <output-type>Analyte</output-type>
        <parent-process uri="http://web-claritytest-01.internal.sanger.ac.uk:8080/api/v2/processes/24-68287" limsid="24-68287"/>
        <qc-flag>UNKNOWN</qc-flag>
        <location>
            <container uri="http://web-claritytest-01.internal.sanger.ac.uk:8080/api/v2/containers/27-14426" limsid="27-14426"/>
            <value>G:2</value>
        </location>
        <working-flag>true</working-flag>
        <sample uri="http://web-claritytest-01.internal.sanger.ac.uk:8080/api/v2/samples/44Y203A14" limsid="44Y203A14"/>
        <workflow-stages/>
    </art:artifact>
    <art:artifact uri="http://web-claritytest-01.internal.sanger.ac.uk:8080/api/v2/artifacts/2-411103?state=210381" limsid="2-411103">
        <name>Fluidigm Analysis File</name>
        <type>Analyte</type>
        <output-type>Analyte</output-type>
        <parent-process uri="http://web-claritytest-01.internal.sanger.ac.uk:8080/api/v2/processes/24-68287" limsid="24-68287"/>
        <qc-flag>UNKNOWN</qc-flag>
        <location>
            <container uri="http://web-claritytest-01.internal.sanger.ac.uk:8080/api/v2/containers/27-14426" limsid="27-14426"/>
            <value>F:4</value>
        </location>
        <working-flag>true</working-flag>
        <sample uri="http://web-claritytest-01.internal.sanger.ac.uk:8080/api/v2/samples/44Y203A15" limsid="44Y203A15"/>
        <workflow-stages/>
    </art:artifact>
    <art:artifact uri="http://web-claritytest-01.internal.sanger.ac.uk:8080/api/v2/artifacts/2-411104?state=210382" limsid="2-411104">
        <name>Fluidigm Analysis File</name>
        <type>Analyte</type>
        <output-type>Analyte</output-type>
        <parent-process uri="http://web-claritytest-01.internal.sanger.ac.uk:8080/api/v2/processes/24-68287" limsid="24-68287"/>
        <qc-flag>UNKNOWN</qc-flag>
        <location>
            <container uri="http://web-claritytest-01.internal.sanger.ac.uk:8080/api/v2/containers/27-14426" limsid="27-14426"/>
            <value>H:3</value>
        </location>
        <working-flag>true</working-flag>
        <sample uri="http://web-claritytest-01.internal.sanger.ac.uk:8080/api/v2/samples/44Y203A12" limsid="44Y203A12"/>
        <workflow-stages/>
    </art:artifact>
    <art:artifact uri="http://web-claritytest-01.internal.sanger.ac.uk:8080/api/v2/artifacts/2-411105?state=210383" limsid="2-411105">
        <name>Fluidigm Analysis File</name>
        <type>Analyte</type>
        <output-type>Analyte</output-type>
        <parent-process uri="http://web-claritytest-01.internal.sanger.ac.uk:8080/api/v2/processes/24-68287" limsid="24-68287"/>
        <qc-flag>UNKNOWN</qc-flag>
        <location>
            <container uri="http://web-claritytest-01.internal.sanger.ac.uk:8080/api/v2/containers/27-14426" limsid="27-14426"/>
            <value>P:2</value>
        </location>
        <working-flag>true</working-flag>
        <sample uri="http://web-claritytest-01.internal.sanger.ac.uk:8080/api/v2/samples/44Y203A13" limsid="44Y203A13"/>
        <workflow-stages/>
    </art:artifact>
    <art:artifact uri="http://web-claritytest-01.internal.sanger.ac.uk:8080/api/v2/artifacts/2-411106?state=210384" limsid="2-411106">
        <name>Fluidigm Analysis File</name>
        <type>Analyte</type>
        <output-type>Analyte</output-type>
        <parent-process uri="http://web-claritytest-01.internal.sanger.ac.uk:8080/api/v2/processes/24-68287" limsid="24-68287"/>
        <qc-flag>UNKNOWN</qc-flag>
        <location>
            <container uri="http://web-claritytest-01.internal.sanger.ac.uk:8080/api/v2/containers/27-14426" limsid="27-14426"/>
            <value>K:4</value>
        </location>
        <working-flag>true</working-flag>
        <sample uri="http://web-claritytest-01.internal.sanger.ac.uk:8080/api/v2/samples/44Y203A7" limsid="44Y203A7"/>
        <workflow-stages/>
    </art:artifact>
    <art:artifact uri="http://web-claritytest-01.internal.sanger.ac.uk:8080/api/v2/artifacts/2-411107?state=210385" limsid="2-411107">
        <name>Fluidigm Analysis File</name>
        <type>Analyte</type>
        <output-type>Analyte</output-type>
        <parent-process uri="http://web-claritytest-01.internal.sanger.ac.uk:8080/api/v2/processes/24-68287" limsid="24-68287"/>
        <qc-flag>UNKNOWN</qc-flag>
        <location>
            <container uri="http://web-claritytest-01.internal.sanger.ac.uk:8080/api/v2/containers/27-14426" limsid="27-14426"/>
            <value>I:6</value>
        </location>
        <working-flag>true</working-flag>
        <sample uri="http://web-claritytest-01.internal.sanger.ac.uk:8080/api/v2/samples/44Y203A6" limsid="44Y203A6"/>
        <workflow-stages/>
    </art:artifact>
    <art:artifact uri="http://web-claritytest-01.internal.sanger.ac.uk:8080/api/v2/artifacts/2-411108?state=210386" limsid="2-411108">
        <name>Fluidigm Analysis File</name>
        <type>Analyte</type>
        <output-type>Analyte</output-type>
        <parent-process uri="http://web-claritytest-01.internal.sanger.ac.uk:8080/api/v2/processes/24-68287" limsid="24-68287"/>
        <qc-flag>UNKNOWN</qc-flag>
        <location>
            <container uri="http://web-claritytest-01.internal.sanger.ac.uk:8080/api/v2/containers/27-14426" limsid="27-14426"/>
            <value>D:1</value>
        </location>
        <working-flag>true</working-flag>
        <sample uri="http://web-claritytest-01.internal.sanger.ac.uk:8080/api/v2/samples/44Y203A5" limsid="44Y203A5"/>
        <workflow-stages/>
    </art:artifact>
    <art:artifact uri="http://web-claritytest-01.internal.sanger.ac.uk:8080/api/v2/artifacts/2-411109?state=210387" limsid="2-411109">
        <name>Fluidigm Analysis File</name>
        <type>Analyte</type>
        <output-type>Analyte</output-type>
        <parent-process uri="http://web-claritytest-01.internal.sanger.ac.uk:8080/api/v2/processes/24-68287" limsid="24-68287"/>
        <qc-flag>UNKNOWN</qc-flag>
        <location>
            <container uri="http://web-claritytest-01.internal.sanger.ac.uk:8080/api/v2/containers/27-14426" limsid="27-14426"/>
            <value>P:1</value>
        </location>
        <working-flag>true</working-flag>
        <sample uri="http://web-claritytest-01.internal.sanger.ac.uk:8080/api/v2/samples/44Y203A4" limsid="44Y203A4"/>
        <workflow-stages/>
    </art:artifact>
    <art:artifact uri="http://web-claritytest-01.internal.sanger.ac.uk:8080/api/v2/artifacts/2-411110?state=210388" limsid="2-411110">
        <name>Fluidigm Analysis File</name>
        <type>Analyte</type>
        <output-type>Analyte</output-type>
        <parent-process uri="http://web-claritytest-01.internal.sanger.ac.uk:8080/api/v2/processes/24-68287" limsid="24-68287"/>
        <qc-flag>UNKNOWN</qc-flag>
        <location>
            <container uri="http://web-claritytest-01.internal.sanger.ac.uk:8080/api/v2/containers/27-14426" limsid="27-14426"/>
            <value>M:4</value>
        </location>
        <working-flag>true</working-flag>
        <sample uri="http://web-claritytest-01.internal.sanger.ac.uk:8080/api/v2/samples/44Y203A17" limsid="44Y203A17"/>
        <workflow-stages/>
    </art:artifact>
    <art:artifact uri="http://web-claritytest-01.internal.sanger.ac.uk:8080/api/v2/artifacts/2-411111?state=210389" limsid="2-411111">
        <name>Fluidigm Analysis File</name>
        <type>Analyte</type>
        <output-type>Analyte</output-type>
        <parent-process uri="http://web-claritytest-01.internal.sanger.ac.uk:8080/api/v2/processes/24-68287" limsid="24-68287"/>
        <qc-flag>UNKNOWN</qc-flag>
        <location>
            <container uri="http://web-claritytest-01.internal.sanger.ac.uk:8080/api/v2/containers/27-14426" limsid="27-14426"/>
            <value>E:5</value>
        </location>
        <working-flag>true</working-flag>
        <sample uri="http://web-claritytest-01.internal.sanger.ac.uk:8080/api/v2/samples/44Y203A19" limsid="44Y203A19"/>
        <workflow-stages/>
    </art:artifact>
    <art:artifact uri="http://web-claritytest-01.internal.sanger.ac.uk:8080/api/v2/artifacts/2-411112?state=210390" limsid="2-411112">
        <name>Fluidigm Analysis File</name>
        <type>Analyte</type>
        <output-type>Analyte</output-type>
        <parent-process uri="http://web-claritytest-01.internal.sanger.ac.uk:8080/api/v2/processes/24-68287" limsid="24-68287"/>
        <qc-flag>UNKNOWN</qc-flag>
        <location>
            <container uri="http://web-claritytest-01.internal.sanger.ac.uk:8080/api/v2/containers/27-14426" limsid="27-14426"/>
            <value>L:4</value>
        </location>
        <working-flag>true</working-flag>
        <sample uri="http://web-claritytest-01.internal.sanger.ac.uk:8080/api/v2/samples/44Y203A18" limsid="44Y203A18"/>
        <workflow-stages/>
    </art:artifact>
    <art:artifact uri="http://web-claritytest-01.internal.sanger.ac.uk:8080/api/v2/artifacts/2-411113?state=210391" limsid="2-411113">
        <name>Fluidigm Analysis File</name>
        <type>Analyte</type>
        <output-type>Analyte</output-type>
        <parent-process uri="http://web-claritytest-01.internal.sanger.ac.uk:8080/api/v2/processes/24-68287" limsid="24-68287"/>
        <qc-flag>UNKNOWN</qc-flag>
        <location>
            <container uri="http://web-claritytest-01.internal.sanger.ac.uk:8080/api/v2/containers/27-14426" limsid="27-14426"/>
            <value>I:4</value>
        </location>
        <working-flag>true</working-flag>
        <sample uri="http://web-claritytest-01.internal.sanger.ac.uk:8080/api/v2/samples/44Y203A21" limsid="44Y203A21"/>
        <workflow-stages/>
    </art:artifact>
    <art:artifact uri="http://web-claritytest-01.internal.sanger.ac.uk:8080/api/v2/artifacts/2-411114?state=210392" limsid="2-411114">
        <name>Fluidigm Analysis File</name>
        <type>Analyte</type>
        <output-type>Analyte</output-type>
        <parent-process uri="http://web-claritytest-01.internal.sanger.ac.uk:8080/api/v2/processes/24-68287" limsid="24-68287"/>
        <qc-flag>UNKNOWN</qc-flag>
        <location>
            <container uri="http://web-claritytest-01.internal.sanger.ac.uk:8080/api/v2/containers/27-14426" limsid="27-14426"/>
            <value>M:2</value>
        </location>
        <working-flag>true</working-flag>
        <sample uri="http://web-claritytest-01.internal.sanger.ac.uk:8080/api/v2/samples/44Y203A20" limsid="44Y203A20"/>
        <workflow-stages/>
    </art:artifact>
    <art:artifact uri="http://web-claritytest-01.internal.sanger.ac.uk:8080/api/v2/artifacts/2-411115?state=210393" limsid="2-411115">
        <name>Fluidigm Analysis File</name>
        <type>Analyte</type>
        <output-type>Analyte</output-type>
        <parent-process uri="http://web-claritytest-01.internal.sanger.ac.uk:8080/api/v2/processes/24-68287" limsid="24-68287"/>
        <qc-flag>UNKNOWN</qc-flag>
        <location>
            <container uri="http://web-claritytest-01.internal.sanger.ac.uk:8080/api/v2/containers/27-14426" limsid="27-14426"/>
            <value>O:3</value>
        </location>
        <working-flag>true</working-flag>
        <sample uri="http://web-claritytest-01.internal.sanger.ac.uk:8080/api/v2/samples/44Y203A23" limsid="44Y203A23"/>
        <workflow-stages/>
    </art:artifact>
    <art:artifact uri="http://web-claritytest-01.internal.sanger.ac.uk:8080/api/v2/artifacts/2-411116?state=210394" limsid="2-411116">
        <name>Fluidigm Analysis File</name>
        <type>Analyte</type>
        <output-type>Analyte</output-type>
        <parent-process uri="http://web-claritytest-01.internal.sanger.ac.uk:8080/api/v2/processes/24-68287" limsid="24-68287"/>
        <qc-flag>UNKNOWN</qc-flag>
        <location>
            <container uri="http://web-claritytest-01.internal.sanger.ac.uk:8080/api/v2/containers/27-14426" limsid="27-14426"/>
            <value>A:2</value>
        </location>
        <working-flag>true</working-flag>
        <sample uri="http://web-claritytest-01.internal.sanger.ac.uk:8080/api/v2/samples/44Y203A22" limsid="44Y203A22"/>
        <workflow-stages/>
    </art:artifact>
    <art:artifact uri="http://web-claritytest-01.internal.sanger.ac.uk:8080/api/v2/artifacts/2-411117?state=210395" limsid="2-411117">
        <name>Fluidigm Analysis File</name>
        <type>Analyte</type>
        <output-type>Analyte</output-type>
        <parent-process uri="http://web-claritytest-01.internal.sanger.ac.uk:8080/api/v2/processes/24-68287" limsid="24-68287"/>
        <qc-flag>UNKNOWN</qc-flag>
        <location>
            <container uri="http://web-claritytest-01.internal.sanger.ac.uk:8080/api/v2/containers/27-14426" limsid="27-14426"/>
            <value>I:1</value>
        </location>
        <working-flag>true</working-flag>
        <sample uri="http://web-claritytest-01.internal.sanger.ac.uk:8080/api/v2/samples/44Y203A25" limsid="44Y203A25"/>
        <workflow-stages/>
    </art:artifact>
    <art:artifact uri="http://web-claritytest-01.internal.sanger.ac.uk:8080/api/v2/artifacts/2-411118?state=210396" limsid="2-411118">
        <name>Fluidigm Analysis File</name>
        <type>Analyte</type>
        <output-type>Analyte</output-type>
        <parent-process uri="http://web-claritytest-01.internal.sanger.ac.uk:8080/api/v2/processes/24-68287" limsid="24-68287"/>
        <qc-flag>UNKNOWN</qc-flag>
        <location>
            <container uri="http://web-claritytest-01.internal.sanger.ac.uk:8080/api/v2/containers/27-14426" limsid="27-14426"/>
            <value>P:4</value>
        </location>
        <working-flag>true</working-flag>
        <sample uri="http://web-claritytest-01.internal.sanger.ac.uk:8080/api/v2/samples/44Y203A24" limsid="44Y203A24"/>
        <workflow-stages/>
    </art:artifact>
    <art:artifact uri="http://web-claritytest-01.internal.sanger.ac.uk:8080/api/v2/artifacts/2-411119?state=210397" limsid="2-411119">
        <name>Fluidigm Analysis File</name>
        <type>Analyte</type>
        <output-type>Analyte</output-type>
        <parent-process uri="http://web-claritytest-01.internal.sanger.ac.uk:8080/api/v2/processes/24-68287" limsid="24-68287"/>
        <qc-flag>UNKNOWN</qc-flag>
        <location>
            <container uri="http://web-claritytest-01.internal.sanger.ac.uk:8080/api/v2/containers/27-14426" limsid="27-14426"/>
            <value>M:3</value>
        </location>
        <working-flag>true</working-flag>
        <sample uri="http://web-claritytest-01.internal.sanger.ac.uk:8080/api/v2/samples/44Y203A62" limsid="44Y203A62"/>
        <workflow-stages/>
    </art:artifact>
    <art:artifact uri="http://web-claritytest-01.internal.sanger.ac.uk:8080/api/v2/artifacts/2-411120?state=210398" limsid="2-411120">
        <name>Fluidigm Analysis File</name>
        <type>Analyte</type>
        <output-type>Analyte</output-type>
        <parent-process uri="http://web-claritytest-01.internal.sanger.ac.uk:8080/api/v2/processes/24-68287" limsid="24-68287"/>
        <qc-flag>UNKNOWN</qc-flag>
        <location>
            <container uri="http://web-claritytest-01.internal.sanger.ac.uk:8080/api/v2/containers/27-14426" limsid="27-14426"/>
            <value>K:5</value>
        </location>
        <working-flag>true</working-flag>
        <sample uri="http://web-claritytest-01.internal.sanger.ac.uk:8080/api/v2/samples/44Y203A63" limsid="44Y203A63"/>
        <workflow-stages/>
    </art:artifact>
    <art:artifact uri="http://web-claritytest-01.internal.sanger.ac.uk:8080/api/v2/artifacts/2-411121?state=210399" limsid="2-411121">
        <name>Fluidigm Analysis File</name>
        <type>Analyte</type>
        <output-type>Analyte</output-type>
        <parent-process uri="http://web-claritytest-01.internal.sanger.ac.uk:8080/api/v2/processes/24-68287" limsid="24-68287"/>
        <qc-flag>UNKNOWN</qc-flag>
        <location>
            <container uri="http://web-claritytest-01.internal.sanger.ac.uk:8080/api/v2/containers/27-14426" limsid="27-14426"/>
            <value>E:4</value>
        </location>
        <working-flag>true</working-flag>
        <sample uri="http://web-claritytest-01.internal.sanger.ac.uk:8080/api/v2/samples/44Y203A64" limsid="44Y203A64"/>
        <workflow-stages/>
    </art:artifact>
    <art:artifact uri="http://web-claritytest-01.internal.sanger.ac.uk:8080/api/v2/artifacts/2-411122?state=210400" limsid="2-411122">
        <name>Fluidigm Analysis File</name>
        <type>Analyte</type>
        <output-type>Analyte</output-type>
        <parent-process uri="http://web-claritytest-01.internal.sanger.ac.uk:8080/api/v2/processes/24-68287" limsid="24-68287"/>
        <qc-flag>UNKNOWN</qc-flag>
        <location>
            <container uri="http://web-claritytest-01.internal.sanger.ac.uk:8080/api/v2/containers/27-14426" limsid="27-14426"/>
            <value>N:4</value>
        </location>
        <working-flag>true</working-flag>
        <sample uri="http://web-claritytest-01.internal.sanger.ac.uk:8080/api/v2/samples/44Y203A65" limsid="44Y203A65"/>
        <workflow-stages/>
    </art:artifact>
    <art:artifact uri="http://web-claritytest-01.internal.sanger.ac.uk:8080/api/v2/artifacts/2-411123?state=210401" limsid="2-411123">
        <name>Fluidigm Analysis File</name>
        <type>Analyte</type>
        <output-type>Analyte</output-type>
        <parent-process uri="http://web-claritytest-01.internal.sanger.ac.uk:8080/api/v2/processes/24-68287" limsid="24-68287"/>
        <qc-flag>UNKNOWN</qc-flag>
        <location>
            <container uri="http://web-claritytest-01.internal.sanger.ac.uk:8080/api/v2/containers/27-14426" limsid="27-14426"/>
            <value>M:5</value>
        </location>
        <working-flag>true</working-flag>
        <sample uri="http://web-claritytest-01.internal.sanger.ac.uk:8080/api/v2/samples/44Y203A58" limsid="44Y203A58"/>
        <workflow-stages/>
    </art:artifact>
    <art:artifact uri="http://web-claritytest-01.internal.sanger.ac.uk:8080/api/v2/artifacts/2-411124?state=210402" limsid="2-411124">
        <name>Fluidigm Analysis File</name>
        <type>Analyte</type>
        <output-type>Analyte</output-type>
        <parent-process uri="http://web-claritytest-01.internal.sanger.ac.uk:8080/api/v2/processes/24-68287" limsid="24-68287"/>
        <qc-flag>UNKNOWN</qc-flag>
        <location>
            <container uri="http://web-claritytest-01.internal.sanger.ac.uk:8080/api/v2/containers/27-14426" limsid="27-14426"/>
            <value>E:1</value>
        </location>
        <working-flag>true</working-flag>
        <sample uri="http://web-claritytest-01.internal.sanger.ac.uk:8080/api/v2/samples/44Y203A59" limsid="44Y203A59"/>
        <workflow-stages/>
    </art:artifact>
    <art:artifact uri="http://web-claritytest-01.internal.sanger.ac.uk:8080/api/v2/artifacts/2-411125?state=210403" limsid="2-411125">
        <name>Fluidigm Analysis File</name>
        <type>Analyte</type>
        <output-type>Analyte</output-type>
        <parent-process uri="http://web-claritytest-01.internal.sanger.ac.uk:8080/api/v2/processes/24-68287" limsid="24-68287"/>
        <qc-flag>UNKNOWN</qc-flag>
        <location>
            <container uri="http://web-claritytest-01.internal.sanger.ac.uk:8080/api/v2/containers/27-14426" limsid="27-14426"/>
            <value>K:2</value>
        </location>
        <working-flag>true</working-flag>
        <sample uri="http://web-claritytest-01.internal.sanger.ac.uk:8080/api/v2/samples/44Y203A60" limsid="44Y203A60"/>
        <workflow-stages/>
    </art:artifact>
    <art:artifact uri="http://web-claritytest-01.internal.sanger.ac.uk:8080/api/v2/artifacts/2-411126?state=210404" limsid="2-411126">
        <name>Fluidigm Analysis File</name>
        <type>Analyte</type>
        <output-type>Analyte</output-type>
        <parent-process uri="http://web-claritytest-01.internal.sanger.ac.uk:8080/api/v2/processes/24-68287" limsid="24-68287"/>
        <qc-flag>UNKNOWN</qc-flag>
        <location>
            <container uri="http://web-claritytest-01.internal.sanger.ac.uk:8080/api/v2/containers/27-14426" limsid="27-14426"/>
            <value>N:1</value>
        </location>
        <working-flag>true</working-flag>
        <sample uri="http://web-claritytest-01.internal.sanger.ac.uk:8080/api/v2/samples/44Y203A61" limsid="44Y203A61"/>
        <workflow-stages/>
    </art:artifact>
    <art:artifact uri="http://web-claritytest-01.internal.sanger.ac.uk:8080/api/v2/artifacts/2-411127?state=210405" limsid="2-411127">
        <name>Fluidigm Analysis File</name>
        <type>Analyte</type>
        <output-type>Analyte</output-type>
        <parent-process uri="http://web-claritytest-01.internal.sanger.ac.uk:8080/api/v2/processes/24-68287" limsid="24-68287"/>
        <qc-flag>UNKNOWN</qc-flag>
        <location>
            <container uri="http://web-claritytest-01.internal.sanger.ac.uk:8080/api/v2/containers/27-14426" limsid="27-14426"/>
            <value>H:2</value>
        </location>
        <working-flag>true</working-flag>
        <sample uri="http://web-claritytest-01.internal.sanger.ac.uk:8080/api/v2/samples/44Y203A70" limsid="44Y203A70"/>
        <workflow-stages/>
    </art:artifact>
    <art:artifact uri="http://web-claritytest-01.internal.sanger.ac.uk:8080/api/v2/artifacts/2-411128?state=210406" limsid="2-411128">
        <name>Fluidigm Analysis File</name>
        <type>Analyte</type>
        <output-type>Analyte</output-type>
        <parent-process uri="http://web-claritytest-01.internal.sanger.ac.uk:8080/api/v2/processes/24-68287" limsid="24-68287"/>
        <qc-flag>UNKNOWN</qc-flag>
        <location>
            <container uri="http://web-claritytest-01.internal.sanger.ac.uk:8080/api/v2/containers/27-14426" limsid="27-14426"/>
            <value>J:3</value>
        </location>
        <working-flag>true</working-flag>
        <sample uri="http://web-claritytest-01.internal.sanger.ac.uk:8080/api/v2/samples/44Y203A71" limsid="44Y203A71"/>
        <workflow-stages/>
    </art:artifact>
    <art:artifact uri="http://web-claritytest-01.internal.sanger.ac.uk:8080/api/v2/artifacts/2-411129?state=210407" limsid="2-411129">
        <name>Fluidigm Analysis File</name>
        <type>Analyte</type>
        <output-type>Analyte</output-type>
        <parent-process uri="http://web-claritytest-01.internal.sanger.ac.uk:8080/api/v2/processes/24-68287" limsid="24-68287"/>
        <qc-flag>UNKNOWN</qc-flag>
        <location>
            <container uri="http://web-claritytest-01.internal.sanger.ac.uk:8080/api/v2/containers/27-14426" limsid="27-14426"/>
            <value>C:2</value>
        </location>
        <working-flag>true</working-flag>
        <sample uri="http://web-claritytest-01.internal.sanger.ac.uk:8080/api/v2/samples/44Y203A72" limsid="44Y203A72"/>
        <workflow-stages/>
    </art:artifact>
    <art:artifact uri="http://web-claritytest-01.internal.sanger.ac.uk:8080/api/v2/artifacts/2-411130?state=210408" limsid="2-411130">
        <name>Fluidigm Analysis File</name>
        <type>Analyte</type>
        <output-type>Analyte</output-type>
        <parent-process uri="http://web-claritytest-01.internal.sanger.ac.uk:8080/api/v2/processes/24-68287" limsid="24-68287"/>
        <qc-flag>UNKNOWN</qc-flag>
        <location>
            <container uri="http://web-claritytest-01.internal.sanger.ac.uk:8080/api/v2/containers/27-14426" limsid="27-14426"/>
            <value>P:3</value>
        </location>
        <working-flag>true</working-flag>
        <sample uri="http://web-claritytest-01.internal.sanger.ac.uk:8080/api/v2/samples/44Y203A73" limsid="44Y203A73"/>
        <workflow-stages/>
    </art:artifact>
    <art:artifact uri="http://web-claritytest-01.internal.sanger.ac.uk:8080/api/v2/artifacts/2-411131?state=210409" limsid="2-411131">
        <name>Fluidigm Analysis File</name>
        <type>Analyte</type>
        <output-type>Analyte</output-type>
        <parent-process uri="http://web-claritytest-01.internal.sanger.ac.uk:8080/api/v2/processes/24-68287" limsid="24-68287"/>
        <qc-flag>UNKNOWN</qc-flag>
        <location>
            <container uri="http://web-claritytest-01.internal.sanger.ac.uk:8080/api/v2/containers/27-14426" limsid="27-14426"/>
            <value>D:5</value>
        </location>
        <working-flag>true</working-flag>
        <sample uri="http://web-claritytest-01.internal.sanger.ac.uk:8080/api/v2/samples/44Y203A66" limsid="44Y203A66"/>
        <workflow-stages/>
    </art:artifact>
    <art:artifact uri="http://web-claritytest-01.internal.sanger.ac.uk:8080/api/v2/artifacts/2-411132?state=210410" limsid="2-411132">
        <name>Fluidigm Analysis File</name>
        <type>Analyte</type>
        <output-type>Analyte</output-type>
        <parent-process uri="http://web-claritytest-01.internal.sanger.ac.uk:8080/api/v2/processes/24-68287" limsid="24-68287"/>
        <qc-flag>UNKNOWN</qc-flag>
        <location>
            <container uri="http://web-claritytest-01.internal.sanger.ac.uk:8080/api/v2/containers/27-14426" limsid="27-14426"/>
            <value>D:4</value>
        </location>
        <working-flag>true</working-flag>
        <sample uri="http://web-claritytest-01.internal.sanger.ac.uk:8080/api/v2/samples/44Y203A68" limsid="44Y203A68"/>
        <workflow-stages/>
    </art:artifact>
    <art:artifact uri="http://web-claritytest-01.internal.sanger.ac.uk:8080/api/v2/artifacts/2-411133?state=210411" limsid="2-411133">
        <name>Fluidigm Analysis File</name>
        <type>Analyte</type>
        <output-type>Analyte</output-type>
        <parent-process uri="http://web-claritytest-01.internal.sanger.ac.uk:8080/api/v2/processes/24-68287" limsid="24-68287"/>
        <qc-flag>UNKNOWN</qc-flag>
        <location>
            <container uri="http://web-claritytest-01.internal.sanger.ac.uk:8080/api/v2/containers/27-14426" limsid="27-14426"/>
            <value>D:3</value>
        </location>
        <working-flag>true</working-flag>
        <sample uri="http://web-claritytest-01.internal.sanger.ac.uk:8080/api/v2/samples/44Y203A69" limsid="44Y203A69"/>
        <workflow-stages/>
    </art:artifact>
    <art:artifact uri="http://web-claritytest-01.internal.sanger.ac.uk:8080/api/v2/artifacts/2-411134?state=210412" limsid="2-411134">
        <name>Fluidigm Analysis File</name>
        <type>Analyte</type>
        <output-type>Analyte</output-type>
        <parent-process uri="http://web-claritytest-01.internal.sanger.ac.uk:8080/api/v2/processes/24-68287" limsid="24-68287"/>
        <qc-flag>UNKNOWN</qc-flag>
        <location>
            <container uri="http://web-claritytest-01.internal.sanger.ac.uk:8080/api/v2/containers/27-14426" limsid="27-14426"/>
            <value>L:1</value>
        </location>
        <working-flag>true</working-flag>
        <sample uri="http://web-claritytest-01.internal.sanger.ac.uk:8080/api/v2/samples/44Y203A79" limsid="44Y203A79"/>
        <workflow-stages/>
    </art:artifact>
    <art:artifact uri="http://web-claritytest-01.internal.sanger.ac.uk:8080/api/v2/artifacts/2-411135?state=210413" limsid="2-411135">
        <name>Fluidigm Analysis File</name>
        <type>Analyte</type>
        <output-type>Analyte</output-type>
        <parent-process uri="http://web-claritytest-01.internal.sanger.ac.uk:8080/api/v2/processes/24-68287" limsid="24-68287"/>
        <qc-flag>UNKNOWN</qc-flag>
        <location>
            <container uri="http://web-claritytest-01.internal.sanger.ac.uk:8080/api/v2/containers/27-14426" limsid="27-14426"/>
            <value>O:2</value>
        </location>
        <working-flag>true</working-flag>
        <sample uri="http://web-claritytest-01.internal.sanger.ac.uk:8080/api/v2/samples/44Y203A78" limsid="44Y203A78"/>
        <workflow-stages/>
    </art:artifact>
    <art:artifact uri="http://web-claritytest-01.internal.sanger.ac.uk:8080/api/v2/artifacts/2-411136?state=210414" limsid="2-411136">
        <name>Fluidigm Analysis File</name>
        <type>Analyte</type>
        <output-type>Analyte</output-type>
        <parent-process uri="http://web-claritytest-01.internal.sanger.ac.uk:8080/api/v2/processes/24-68287" limsid="24-68287"/>
        <qc-flag>UNKNOWN</qc-flag>
        <location>
            <container uri="http://web-claritytest-01.internal.sanger.ac.uk:8080/api/v2/containers/27-14426" limsid="27-14426"/>
            <value>M:6</value>
        </location>
        <working-flag>true</working-flag>
        <sample uri="http://web-claritytest-01.internal.sanger.ac.uk:8080/api/v2/samples/44Y203A81" limsid="44Y203A81"/>
        <workflow-stages/>
    </art:artifact>
    <art:artifact uri="http://web-claritytest-01.internal.sanger.ac.uk:8080/api/v2/artifacts/2-411137?state=210415" limsid="2-411137">
        <name>Fluidigm Analysis File</name>
        <type>Analyte</type>
        <output-type>Analyte</output-type>
        <parent-process uri="http://web-claritytest-01.internal.sanger.ac.uk:8080/api/v2/processes/24-68287" limsid="24-68287"/>
        <qc-flag>UNKNOWN</qc-flag>
        <location>
            <container uri="http://web-claritytest-01.internal.sanger.ac.uk:8080/api/v2/containers/27-14426" limsid="27-14426"/>
            <value>J:1</value>
        </location>
        <working-flag>true</working-flag>
        <sample uri="http://web-claritytest-01.internal.sanger.ac.uk:8080/api/v2/samples/44Y203A80" limsid="44Y203A80"/>
        <workflow-stages/>
    </art:artifact>
    <art:artifact uri="http://web-claritytest-01.internal.sanger.ac.uk:8080/api/v2/artifacts/2-411138?state=210416" limsid="2-411138">
        <name>Fluidigm Analysis File</name>
        <type>Analyte</type>
        <output-type>Analyte</output-type>
        <parent-process uri="http://web-claritytest-01.internal.sanger.ac.uk:8080/api/v2/processes/24-68287" limsid="24-68287"/>
        <qc-flag>UNKNOWN</qc-flag>
        <location>
            <container uri="http://web-claritytest-01.internal.sanger.ac.uk:8080/api/v2/containers/27-14426" limsid="27-14426"/>
            <value>G:4</value>
        </location>
        <working-flag>true</working-flag>
        <sample uri="http://web-claritytest-01.internal.sanger.ac.uk:8080/api/v2/samples/44Y203A75" limsid="44Y203A75"/>
        <workflow-stages/>
    </art:artifact>
    <art:artifact uri="http://web-claritytest-01.internal.sanger.ac.uk:8080/api/v2/artifacts/2-411139?state=210417" limsid="2-411139">
        <name>Fluidigm Analysis File</name>
        <type>Analyte</type>
        <output-type>Analyte</output-type>
        <parent-process uri="http://web-claritytest-01.internal.sanger.ac.uk:8080/api/v2/processes/24-68287" limsid="24-68287"/>
        <qc-flag>UNKNOWN</qc-flag>
        <location>
            <container uri="http://web-claritytest-01.internal.sanger.ac.uk:8080/api/v2/containers/27-14426" limsid="27-14426"/>
            <value>J:2</value>
        </location>
        <working-flag>true</working-flag>
        <sample uri="http://web-claritytest-01.internal.sanger.ac.uk:8080/api/v2/samples/44Y203A74" limsid="44Y203A74"/>
        <workflow-stages/>
    </art:artifact>
    <art:artifact uri="http://web-claritytest-01.internal.sanger.ac.uk:8080/api/v2/artifacts/2-411140?state=210418" limsid="2-411140">
        <name>Fluidigm Analysis File</name>
        <type>Analyte</type>
        <output-type>Analyte</output-type>
        <parent-process uri="http://web-claritytest-01.internal.sanger.ac.uk:8080/api/v2/processes/24-68287" limsid="24-68287"/>
        <qc-flag>UNKNOWN</qc-flag>
        <location>
            <container uri="http://web-claritytest-01.internal.sanger.ac.uk:8080/api/v2/containers/27-14426" limsid="27-14426"/>
            <value>A:4</value>
        </location>
        <working-flag>true</working-flag>
        <sample uri="http://web-claritytest-01.internal.sanger.ac.uk:8080/api/v2/samples/44Y203A77" limsid="44Y203A77"/>
        <workflow-stages/>
    </art:artifact>
    <art:artifact uri="http://web-claritytest-01.internal.sanger.ac.uk:8080/api/v2/artifacts/2-411141?state=210419" limsid="2-411141">
        <name>Fluidigm Analysis File</name>
        <type>Analyte</type>
        <output-type>Analyte</output-type>
        <parent-process uri="http://web-claritytest-01.internal.sanger.ac.uk:8080/api/v2/processes/24-68287" limsid="24-68287"/>
        <qc-flag>UNKNOWN</qc-flag>
        <location>
            <container uri="http://web-claritytest-01.internal.sanger.ac.uk:8080/api/v2/containers/27-14426" limsid="27-14426"/>
            <value>L:2</value>
        </location>
        <working-flag>true</working-flag>
        <sample uri="http://web-claritytest-01.internal.sanger.ac.uk:8080/api/v2/samples/44Y203A76" limsid="44Y203A76"/>
        <workflow-stages/>
    </art:artifact>
    <art:artifact uri="http://web-claritytest-01.internal.sanger.ac.uk:8080/api/v2/artifacts/2-411142?state=210420" limsid="2-411142">
        <name>Fluidigm Analysis File</name>
        <type>Analyte</type>
        <output-type>Analyte</output-type>
        <parent-process uri="http://web-claritytest-01.internal.sanger.ac.uk:8080/api/v2/processes/24-68287" limsid="24-68287"/>
        <qc-flag>UNKNOWN</qc-flag>
        <location>
            <container uri="http://web-claritytest-01.internal.sanger.ac.uk:8080/api/v2/containers/27-14426" limsid="27-14426"/>
            <value>A:3</value>
        </location>
        <working-flag>true</working-flag>
        <sample uri="http://web-claritytest-01.internal.sanger.ac.uk:8080/api/v2/samples/44Y203A87" limsid="44Y203A87"/>
        <workflow-stages/>
    </art:artifact>
    <art:artifact uri="http://web-claritytest-01.internal.sanger.ac.uk:8080/api/v2/artifacts/2-411143?state=210421" limsid="2-411143">
        <name>Fluidigm Analysis File</name>
        <type>Analyte</type>
        <output-type>Analyte</output-type>
        <parent-process uri="http://web-claritytest-01.internal.sanger.ac.uk:8080/api/v2/processes/24-68287" limsid="24-68287"/>
        <qc-flag>UNKNOWN</qc-flag>
        <location>
            <container uri="http://web-claritytest-01.internal.sanger.ac.uk:8080/api/v2/containers/27-14426" limsid="27-14426"/>
            <value>C:4</value>
        </location>
        <working-flag>true</working-flag>
        <sample uri="http://web-claritytest-01.internal.sanger.ac.uk:8080/api/v2/samples/44Y203A86" limsid="44Y203A86"/>
        <workflow-stages/>
    </art:artifact>
    <art:artifact uri="http://web-claritytest-01.internal.sanger.ac.uk:8080/api/v2/artifacts/2-411144?state=210422" limsid="2-411144">
        <name>Fluidigm Analysis File</name>
        <type>Analyte</type>
        <output-type>Analyte</output-type>
        <parent-process uri="http://web-claritytest-01.internal.sanger.ac.uk:8080/api/v2/processes/24-68287" limsid="24-68287"/>
        <qc-flag>UNKNOWN</qc-flag>
        <location>
            <container uri="http://web-claritytest-01.internal.sanger.ac.uk:8080/api/v2/containers/27-14426" limsid="27-14426"/>
            <value>O:4</value>
        </location>
        <working-flag>true</working-flag>
        <sample uri="http://web-claritytest-01.internal.sanger.ac.uk:8080/api/v2/samples/44Y203A83" limsid="44Y203A83"/>
        <workflow-stages/>
    </art:artifact>
    <art:artifact uri="http://web-claritytest-01.internal.sanger.ac.uk:8080/api/v2/artifacts/2-411145?state=210423" limsid="2-411145">
        <name>Fluidigm Analysis File</name>
        <type>Analyte</type>
        <output-type>Analyte</output-type>
        <parent-process uri="http://web-claritytest-01.internal.sanger.ac.uk:8080/api/v2/processes/24-68287" limsid="24-68287"/>
        <qc-flag>UNKNOWN</qc-flag>
        <location>
            <container uri="http://web-claritytest-01.internal.sanger.ac.uk:8080/api/v2/containers/27-14426" limsid="27-14426"/>
            <value>F:5</value>
        </location>
        <working-flag>true</working-flag>
        <sample uri="http://web-claritytest-01.internal.sanger.ac.uk:8080/api/v2/samples/44Y203A82" limsid="44Y203A82"/>
        <workflow-stages/>
    </art:artifact>
    <art:artifact uri="http://web-claritytest-01.internal.sanger.ac.uk:8080/api/v2/artifacts/2-411146?state=210424" limsid="2-411146">
        <name>Fluidigm Analysis File</name>
        <type>Analyte</type>
        <output-type>Analyte</output-type>
        <parent-process uri="http://web-claritytest-01.internal.sanger.ac.uk:8080/api/v2/processes/24-68287" limsid="24-68287"/>
        <qc-flag>UNKNOWN</qc-flag>
        <location>
            <container uri="http://web-claritytest-01.internal.sanger.ac.uk:8080/api/v2/containers/27-14426" limsid="27-14426"/>
            <value>I:2</value>
        </location>
        <working-flag>true</working-flag>
        <sample uri="http://web-claritytest-01.internal.sanger.ac.uk:8080/api/v2/samples/44Y203A85" limsid="44Y203A85"/>
        <workflow-stages/>
    </art:artifact>
    <art:artifact uri="http://web-claritytest-01.internal.sanger.ac.uk:8080/api/v2/artifacts/2-411147?state=210425" limsid="2-411147">
        <name>Fluidigm Analysis File</name>
        <type>Analyte</type>
        <output-type>Analyte</output-type>
        <parent-process uri="http://web-claritytest-01.internal.sanger.ac.uk:8080/api/v2/processes/24-68287" limsid="24-68287"/>
        <qc-flag>UNKNOWN</qc-flag>
        <location>
            <container uri="http://web-claritytest-01.internal.sanger.ac.uk:8080/api/v2/containers/27-14426" limsid="27-14426"/>
            <value>B:3</value>
        </location>
        <working-flag>true</working-flag>
        <sample uri="http://web-claritytest-01.internal.sanger.ac.uk:8080/api/v2/samples/44Y203A84" limsid="44Y203A84"/>
        <workflow-stages/>
    </art:artifact>
    <art:artifact uri="http://web-claritytest-01.internal.sanger.ac.uk:8080/api/v2/artifacts/2-411148?state=210426" limsid="2-411148">
        <name>Fluidigm Analysis File</name>
        <type>Analyte</type>
        <output-type>Analyte</output-type>
        <parent-process uri="http://web-claritytest-01.internal.sanger.ac.uk:8080/api/v2/processes/24-68287" limsid="24-68287"/>
        <qc-flag>UNKNOWN</qc-flag>
        <location>
            <container uri="http://web-claritytest-01.internal.sanger.ac.uk:8080/api/v2/containers/27-14426" limsid="27-14426"/>
            <value>C:3</value>
        </location>
        <working-flag>true</working-flag>
        <sample uri="http://web-claritytest-01.internal.sanger.ac.uk:8080/api/v2/samples/44Y203A32" limsid="44Y203A32"/>
        <workflow-stages/>
    </art:artifact>
    <art:artifact uri="http://web-claritytest-01.internal.sanger.ac.uk:8080/api/v2/artifacts/2-411149?state=210427" limsid="2-411149">
        <name>Fluidigm Analysis File</name>
        <type>Analyte</type>
        <output-type>Analyte</output-type>
        <parent-process uri="http://web-claritytest-01.internal.sanger.ac.uk:8080/api/v2/processes/24-68287" limsid="24-68287"/>
        <qc-flag>UNKNOWN</qc-flag>
        <location>
            <container uri="http://web-claritytest-01.internal.sanger.ac.uk:8080/api/v2/containers/27-14426" limsid="27-14426"/>
            <value>O:1</value>
        </location>
        <working-flag>true</working-flag>
        <sample uri="http://web-claritytest-01.internal.sanger.ac.uk:8080/api/v2/samples/44Y203A33" limsid="44Y203A33"/>
        <workflow-stages/>
    </art:artifact>
    <art:artifact uri="http://web-claritytest-01.internal.sanger.ac.uk:8080/api/v2/artifacts/2-411150?state=210428" limsid="2-411150">
        <name>Fluidigm Analysis File</name>
        <type>Analyte</type>
        <output-type>Analyte</output-type>
        <parent-process uri="http://web-claritytest-01.internal.sanger.ac.uk:8080/api/v2/processes/24-68287" limsid="24-68287"/>
        <qc-flag>UNKNOWN</qc-flag>
        <location>
            <container uri="http://web-claritytest-01.internal.sanger.ac.uk:8080/api/v2/containers/27-14426" limsid="27-14426"/>
            <value>N:3</value>
        </location>
        <working-flag>true</working-flag>
        <sample uri="http://web-claritytest-01.internal.sanger.ac.uk:8080/api/v2/samples/44Y203A30" limsid="44Y203A30"/>
        <workflow-stages/>
    </art:artifact>
    <art:artifact uri="http://web-claritytest-01.internal.sanger.ac.uk:8080/api/v2/artifacts/2-411201?state=210429" limsid="2-411201">
        <name>Fluidigm Analysis File</name>
        <type>Analyte</type>
        <output-type>Analyte</output-type>
        <parent-process uri="http://web-claritytest-01.internal.sanger.ac.uk:8080/api/v2/processes/24-68287" limsid="24-68287"/>
        <qc-flag>UNKNOWN</qc-flag>
        <location>
            <container uri="http://web-claritytest-01.internal.sanger.ac.uk:8080/api/v2/containers/27-14426" limsid="27-14426"/>
            <value>J:4</value>
        </location>
        <working-flag>true</working-flag>
        <sample uri="http://web-claritytest-01.internal.sanger.ac.uk:8080/api/v2/samples/44Y203A31" limsid="44Y203A31"/>
        <workflow-stages/>
    </art:artifact>
    <art:artifact uri="http://web-claritytest-01.internal.sanger.ac.uk:8080/api/v2/artifacts/2-411202?state=210430" limsid="2-411202">
        <name>Fluidigm Analysis File</name>
        <type>Analyte</type>
        <output-type>Analyte</output-type>
        <parent-process uri="http://web-claritytest-01.internal.sanger.ac.uk:8080/api/v2/processes/24-68287" limsid="24-68287"/>
        <qc-flag>UNKNOWN</qc-flag>
        <location>
            <container uri="http://web-claritytest-01.internal.sanger.ac.uk:8080/api/v2/containers/27-14426" limsid="27-14426"/>
            <value>I:5</value>
        </location>
        <working-flag>true</working-flag>
        <sample uri="http://web-claritytest-01.internal.sanger.ac.uk:8080/api/v2/samples/44Y203A28" limsid="44Y203A28"/>
        <workflow-stages/>
    </art:artifact>
    <art:artifact uri="http://web-claritytest-01.internal.sanger.ac.uk:8080/api/v2/artifacts/2-411203?state=210431" limsid="2-411203">
        <name>Fluidigm Analysis File</name>
        <type>Analyte</type>
        <output-type>Analyte</output-type>
        <parent-process uri="http://web-claritytest-01.internal.sanger.ac.uk:8080/api/v2/processes/24-68287" limsid="24-68287"/>
        <qc-flag>UNKNOWN</qc-flag>
        <location>
            <container uri="http://web-claritytest-01.internal.sanger.ac.uk:8080/api/v2/containers/27-14426" limsid="27-14426"/>
            <value>F:2</value>
        </location>
        <working-flag>true</working-flag>
        <sample uri="http://web-claritytest-01.internal.sanger.ac.uk:8080/api/v2/samples/44Y203A29" limsid="44Y203A29"/>
        <workflow-stages/>
    </art:artifact>
    <art:artifact uri="http://web-claritytest-01.internal.sanger.ac.uk:8080/api/v2/artifacts/2-411204?state=210432" limsid="2-411204">
        <name>Fluidigm Analysis File</name>
        <type>Analyte</type>
        <output-type>Analyte</output-type>
        <parent-process uri="http://web-claritytest-01.internal.sanger.ac.uk:8080/api/v2/processes/24-68287" limsid="24-68287"/>
        <qc-flag>UNKNOWN</qc-flag>
        <location>
            <container uri="http://web-claritytest-01.internal.sanger.ac.uk:8080/api/v2/containers/27-14426" limsid="27-14426"/>
            <value>E:2</value>
        </location>
        <working-flag>true</working-flag>
        <sample uri="http://web-claritytest-01.internal.sanger.ac.uk:8080/api/v2/samples/44Y203A26" limsid="44Y203A26"/>
        <workflow-stages/>
    </art:artifact>
    <art:artifact uri="http://web-claritytest-01.internal.sanger.ac.uk:8080/api/v2/artifacts/2-411205?state=210433" limsid="2-411205">
        <name>Fluidigm Analysis File</name>
        <type>Analyte</type>
        <output-type>Analyte</output-type>
        <parent-process uri="http://web-claritytest-01.internal.sanger.ac.uk:8080/api/v2/processes/24-68287" limsid="24-68287"/>
        <qc-flag>UNKNOWN</qc-flag>
        <location>
            <container uri="http://web-claritytest-01.internal.sanger.ac.uk:8080/api/v2/containers/27-14426" limsid="27-14426"/>
            <value>N:2</value>
        </location>
        <working-flag>true</working-flag>
        <sample uri="http://web-claritytest-01.internal.sanger.ac.uk:8080/api/v2/samples/44Y203A27" limsid="44Y203A27"/>
        <workflow-stages/>
    </art:artifact>
    <art:artifact uri="http://web-claritytest-01.internal.sanger.ac.uk:8080/api/v2/artifacts/2-411206?state=210434" limsid="2-411206">
        <name>Fluidigm Analysis File</name>
        <type>Analyte</type>
        <output-type>Analyte</output-type>
        <parent-process uri="http://web-claritytest-01.internal.sanger.ac.uk:8080/api/v2/processes/24-68287" limsid="24-68287"/>
        <qc-flag>UNKNOWN</qc-flag>
        <location>
            <container uri="http://web-claritytest-01.internal.sanger.ac.uk:8080/api/v2/containers/27-14426" limsid="27-14426"/>
            <value>I:3</value>
        </location>
        <working-flag>true</working-flag>
        <sample uri="http://web-claritytest-01.internal.sanger.ac.uk:8080/api/v2/samples/44Y203A41" limsid="44Y203A41"/>
        <workflow-stages/>
    </art:artifact>
    <art:artifact uri="http://web-claritytest-01.internal.sanger.ac.uk:8080/api/v2/artifacts/2-411207?state=210435" limsid="2-411207">
        <name>Fluidigm Analysis File</name>
        <type>Analyte</type>
        <output-type>Analyte</output-type>
        <parent-process uri="http://web-claritytest-01.internal.sanger.ac.uk:8080/api/v2/processes/24-68287" limsid="24-68287"/>
        <qc-flag>UNKNOWN</qc-flag>
        <location>
            <container uri="http://web-claritytest-01.internal.sanger.ac.uk:8080/api/v2/containers/27-14426" limsid="27-14426"/>
            <value>C:1</value>
        </location>
        <working-flag>true</working-flag>
        <sample uri="http://web-claritytest-01.internal.sanger.ac.uk:8080/api/v2/samples/44Y203A38" limsid="44Y203A38"/>
        <workflow-stages/>
    </art:artifact>
    <art:artifact uri="http://web-claritytest-01.internal.sanger.ac.uk:8080/api/v2/artifacts/2-411208?state=210436" limsid="2-411208">
        <name>Fluidigm Analysis File</name>
        <type>Analyte</type>
        <output-type>Analyte</output-type>
        <parent-process uri="http://web-claritytest-01.internal.sanger.ac.uk:8080/api/v2/processes/24-68287" limsid="24-68287"/>
        <qc-flag>UNKNOWN</qc-flag>
        <location>
            <container uri="http://web-claritytest-01.internal.sanger.ac.uk:8080/api/v2/containers/27-14426" limsid="27-14426"/>
            <value>O:5</value>
        </location>
        <working-flag>true</working-flag>
        <sample uri="http://web-claritytest-01.internal.sanger.ac.uk:8080/api/v2/samples/44Y203A39" limsid="44Y203A39"/>
        <workflow-stages/>
    </art:artifact>
    <art:artifact uri="http://web-claritytest-01.internal.sanger.ac.uk:8080/api/v2/artifacts/2-411209?state=210437" limsid="2-411209">
        <name>Fluidigm Analysis File</name>
        <type>Analyte</type>
        <output-type>Analyte</output-type>
        <parent-process uri="http://web-claritytest-01.internal.sanger.ac.uk:8080/api/v2/processes/24-68287" limsid="24-68287"/>
        <qc-flag>UNKNOWN</qc-flag>
        <location>
            <container uri="http://web-claritytest-01.internal.sanger.ac.uk:8080/api/v2/containers/27-14426" limsid="27-14426"/>
            <value>A:5</value>
        </location>
        <working-flag>true</working-flag>
        <sample uri="http://web-claritytest-01.internal.sanger.ac.uk:8080/api/v2/samples/44Y203A36" limsid="44Y203A36"/>
        <workflow-stages/>
    </art:artifact>
    <art:artifact uri="http://web-claritytest-01.internal.sanger.ac.uk:8080/api/v2/artifacts/2-411210?state=210438" limsid="2-411210">
        <name>Fluidigm Analysis File</name>
        <type>Analyte</type>
        <output-type>Analyte</output-type>
        <parent-process uri="http://web-claritytest-01.internal.sanger.ac.uk:8080/api/v2/processes/24-68287" limsid="24-68287"/>
        <qc-flag>UNKNOWN</qc-flag>
        <location>
            <container uri="http://web-claritytest-01.internal.sanger.ac.uk:8080/api/v2/containers/27-14426" limsid="27-14426"/>
            <value>F:3</value>
        </location>
        <working-flag>true</working-flag>
        <sample uri="http://web-claritytest-01.internal.sanger.ac.uk:8080/api/v2/samples/44Y203A37" limsid="44Y203A37"/>
        <workflow-stages/>
    </art:artifact>
    <art:artifact uri="http://web-claritytest-01.internal.sanger.ac.uk:8080/api/v2/artifacts/2-411211?state=210439" limsid="2-411211">
        <name>Fluidigm Analysis File</name>
        <type>Analyte</type>
        <output-type>Analyte</output-type>
        <parent-process uri="http://web-claritytest-01.internal.sanger.ac.uk:8080/api/v2/processes/24-68287" limsid="24-68287"/>
        <qc-flag>UNKNOWN</qc-flag>
        <location>
            <container uri="http://web-claritytest-01.internal.sanger.ac.uk:8080/api/v2/containers/27-14426" limsid="27-14426"/>
            <value>K:6</value>
        </location>
        <working-flag>true</working-flag>
        <sample uri="http://web-claritytest-01.internal.sanger.ac.uk:8080/api/v2/samples/44Y203A34" limsid="44Y203A34"/>
        <workflow-stages/>
    </art:artifact>
    <art:artifact uri="http://web-claritytest-01.internal.sanger.ac.uk:8080/api/v2/artifacts/2-411212?state=210440" limsid="2-411212">
        <name>Fluidigm Analysis File</name>
        <type>Analyte</type>
        <output-type>Analyte</output-type>
        <parent-process uri="http://web-claritytest-01.internal.sanger.ac.uk:8080/api/v2/processes/24-68287" limsid="24-68287"/>
        <qc-flag>UNKNOWN</qc-flag>
        <location>
            <container uri="http://web-claritytest-01.internal.sanger.ac.uk:8080/api/v2/containers/27-14426" limsid="27-14426"/>
            <value>B:5</value>
        </location>
        <working-flag>true</working-flag>
        <sample uri="http://web-claritytest-01.internal.sanger.ac.uk:8080/api/v2/samples/44Y203A35" limsid="44Y203A35"/>
        <workflow-stages/>
    </art:artifact>
    <art:artifact uri="http://web-claritytest-01.internal.sanger.ac.uk:8080/api/v2/artifacts/2-411213?state=210441" limsid="2-411213">
        <name>Fluidigm Analysis File</name>
        <type>Analyte</type>
        <output-type>Analyte</output-type>
        <parent-process uri="http://web-claritytest-01.internal.sanger.ac.uk:8080/api/v2/processes/24-68287" limsid="24-68287"/>
        <qc-flag>UNKNOWN</qc-flag>
        <location>
            <container uri="http://web-claritytest-01.internal.sanger.ac.uk:8080/api/v2/containers/27-14426" limsid="27-14426"/>
            <value>K:3</value>
        </location>
        <working-flag>true</working-flag>
        <sample uri="http://web-claritytest-01.internal.sanger.ac.uk:8080/api/v2/samples/44Y203A49" limsid="44Y203A49"/>
        <workflow-stages/>
    </art:artifact>
    <art:artifact uri="http://web-claritytest-01.internal.sanger.ac.uk:8080/api/v2/artifacts/2-411214?state=210442" limsid="2-411214">
        <name>Fluidigm Analysis File</name>
        <type>Analyte</type>
        <output-type>Analyte</output-type>
        <parent-process uri="http://web-claritytest-01.internal.sanger.ac.uk:8080/api/v2/processes/24-68287" limsid="24-68287"/>
        <qc-flag>UNKNOWN</qc-flag>
        <location>
            <container uri="http://web-claritytest-01.internal.sanger.ac.uk:8080/api/v2/containers/27-14426" limsid="27-14426"/>
            <value>B:4</value>
        </location>
        <working-flag>true</working-flag>
        <sample uri="http://web-claritytest-01.internal.sanger.ac.uk:8080/api/v2/samples/44Y203A48" limsid="44Y203A48"/>
        <workflow-stages/>
    </art:artifact>
    <art:artifact uri="http://web-claritytest-01.internal.sanger.ac.uk:8080/api/v2/artifacts/2-411215?state=210443" limsid="2-411215">
        <name>Fluidigm Analysis File</name>
        <type>Analyte</type>
        <output-type>Analyte</output-type>
        <parent-process uri="http://web-claritytest-01.internal.sanger.ac.uk:8080/api/v2/processes/24-68287" limsid="24-68287"/>
        <qc-flag>UNKNOWN</qc-flag>
        <location>
            <container uri="http://web-claritytest-01.internal.sanger.ac.uk:8080/api/v2/containers/27-14426" limsid="27-14426"/>
            <value>O:6</value>
        </location>
        <working-flag>true</working-flag>
        <sample uri="http://web-claritytest-01.internal.sanger.ac.uk:8080/api/v2/samples/44Y203A47" limsid="44Y203A47"/>
        <workflow-stages/>
    </art:artifact>
    <art:artifact uri="http://web-claritytest-01.internal.sanger.ac.uk:8080/api/v2/artifacts/2-411216?state=210444" limsid="2-411216">
        <name>Fluidigm Analysis File</name>
        <type>Analyte</type>
        <output-type>Analyte</output-type>
        <parent-process uri="http://web-claritytest-01.internal.sanger.ac.uk:8080/api/v2/processes/24-68287" limsid="24-68287"/>
        <qc-flag>UNKNOWN</qc-flag>
        <location>
            <container uri="http://web-claritytest-01.internal.sanger.ac.uk:8080/api/v2/containers/27-14426" limsid="27-14426"/>
            <value>H:1</value>
        </location>
        <working-flag>true</working-flag>
        <sample uri="http://web-claritytest-01.internal.sanger.ac.uk:8080/api/v2/samples/44Y203A46" limsid="44Y203A46"/>
        <workflow-stages/>
    </art:artifact>
    <art:artifact uri="http://web-claritytest-01.internal.sanger.ac.uk:8080/api/v2/artifacts/2-411217?state=210445" limsid="2-411217">
        <name>Fluidigm Analysis File</name>
        <type>Analyte</type>
        <output-type>Analyte</output-type>
        <parent-process uri="http://web-claritytest-01.internal.sanger.ac.uk:8080/api/v2/processes/24-68287" limsid="24-68287"/>
        <qc-flag>UNKNOWN</qc-flag>
        <location>
            <container uri="http://web-claritytest-01.internal.sanger.ac.uk:8080/api/v2/containers/27-14426" limsid="27-14426"/>
            <value>H:5</value>
        </location>
        <working-flag>true</working-flag>
        <sample uri="http://web-claritytest-01.internal.sanger.ac.uk:8080/api/v2/samples/44Y203A44" limsid="44Y203A44"/>
        <workflow-stages/>
    </art:artifact>
    <art:artifact uri="http://web-claritytest-01.internal.sanger.ac.uk:8080/api/v2/artifacts/2-411218?state=210446" limsid="2-411218">
        <name>Fluidigm Analysis File</name>
        <type>Analyte</type>
        <output-type>Analyte</output-type>
        <parent-process uri="http://web-claritytest-01.internal.sanger.ac.uk:8080/api/v2/processes/24-68287" limsid="24-68287"/>
        <qc-flag>UNKNOWN</qc-flag>
        <location>
            <container uri="http://web-claritytest-01.internal.sanger.ac.uk:8080/api/v2/containers/27-14426" limsid="27-14426"/>
            <value>G:3</value>
        </location>
        <working-flag>true</working-flag>
        <sample uri="http://web-claritytest-01.internal.sanger.ac.uk:8080/api/v2/samples/44Y203A43" limsid="44Y203A43"/>
        <workflow-stages/>
    </art:artifact>
    <art:artifact uri="http://web-claritytest-01.internal.sanger.ac.uk:8080/api/v2/artifacts/2-411219?state=210447" limsid="2-411219">
        <name>Fluidigm Analysis File</name>
        <type>Analyte</type>
        <output-type>Analyte</output-type>
        <parent-process uri="http://web-claritytest-01.internal.sanger.ac.uk:8080/api/v2/processes/24-68287" limsid="24-68287"/>
        <qc-flag>UNKNOWN</qc-flag>
        <location>
            <container uri="http://web-claritytest-01.internal.sanger.ac.uk:8080/api/v2/containers/27-14426" limsid="27-14426"/>
            <value>M:1</value>
        </location>
        <working-flag>true</working-flag>
        <sample uri="http://web-claritytest-01.internal.sanger.ac.uk:8080/api/v2/samples/44Y203A42" limsid="44Y203A42"/>
        <workflow-stages/>
    </art:artifact>
    <art:artifact uri="http://web-claritytest-01.internal.sanger.ac.uk:8080/api/v2/artifacts/2-411220?state=210448" limsid="2-411220">
        <name>Fluidigm Analysis File</name>
        <type>Analyte</type>
        <output-type>Analyte</output-type>
        <parent-process uri="http://web-claritytest-01.internal.sanger.ac.uk:8080/api/v2/processes/24-68287" limsid="24-68287"/>
        <qc-flag>UNKNOWN</qc-flag>
        <location>
            <container uri="http://web-claritytest-01.internal.sanger.ac.uk:8080/api/v2/containers/27-14426" limsid="27-14426"/>
            <value>F:1</value>
        </location>
        <working-flag>true</working-flag>
        <sample uri="http://web-claritytest-01.internal.sanger.ac.uk:8080/api/v2/samples/44Y203A57" limsid="44Y203A57"/>
        <workflow-stages/>
    </art:artifact>
    <art:artifact uri="http://web-claritytest-01.internal.sanger.ac.uk:8080/api/v2/artifacts/2-411221?state=210449" limsid="2-411221">
        <name>Fluidigm Analysis File</name>
        <type>Analyte</type>
        <output-type>Analyte</output-type>
        <parent-process uri="http://web-claritytest-01.internal.sanger.ac.uk:8080/api/v2/processes/24-68287" limsid="24-68287"/>
        <qc-flag>UNKNOWN</qc-flag>
        <location>
            <container uri="http://web-claritytest-01.internal.sanger.ac.uk:8080/api/v2/containers/27-14426" limsid="27-14426"/>
            <value>A:1</value>
        </location>
        <working-flag>true</working-flag>
        <sample uri="http://web-claritytest-01.internal.sanger.ac.uk:8080/api/v2/samples/44Y203A56" limsid="44Y203A56"/>
        <workflow-stages/>
    </art:artifact>
    <art:artifact uri="http://web-claritytest-01.internal.sanger.ac.uk:8080/api/v2/artifacts/2-411222?state=210450" limsid="2-411222">
        <name>Fluidigm Analysis File</name>
        <type>Analyte</type>
        <output-type>Analyte</output-type>
        <parent-process uri="http://web-claritytest-01.internal.sanger.ac.uk:8080/api/v2/processes/24-68287" limsid="24-68287"/>
        <qc-flag>UNKNOWN</qc-flag>
        <location>
            <container uri="http://web-claritytest-01.internal.sanger.ac.uk:8080/api/v2/containers/27-14426" limsid="27-14426"/>
            <value>J:5</value>
        </location>
        <working-flag>true</working-flag>
        <sample uri="http://web-claritytest-01.internal.sanger.ac.uk:8080/api/v2/samples/44Y203A55" limsid="44Y203A55"/>
        <workflow-stages/>
    </art:artifact>
    <art:artifact uri="http://web-claritytest-01.internal.sanger.ac.uk:8080/api/v2/artifacts/2-411223?state=210451" limsid="2-411223">
        <name>Fluidigm Analysis File</name>
        <type>Analyte</type>
        <output-type>Analyte</output-type>
        <parent-process uri="http://web-claritytest-01.internal.sanger.ac.uk:8080/api/v2/processes/24-68287" limsid="24-68287"/>
        <qc-flag>UNKNOWN</qc-flag>
        <location>
            <container uri="http://web-claritytest-01.internal.sanger.ac.uk:8080/api/v2/containers/27-14426" limsid="27-14426"/>
            <value>L:3</value>
        </location>
        <working-flag>true</working-flag>
        <sample uri="http://web-claritytest-01.internal.sanger.ac.uk:8080/api/v2/samples/44Y203A54" limsid="44Y203A54"/>
        <workflow-stages/>
    </art:artifact>
    <art:artifact uri="http://web-claritytest-01.internal.sanger.ac.uk:8080/api/v2/artifacts/2-411224?state=210452" limsid="2-411224">
        <name>Fluidigm Analysis File</name>
        <type>Analyte</type>
        <output-type>Analyte</output-type>
        <parent-process uri="http://web-claritytest-01.internal.sanger.ac.uk:8080/api/v2/processes/24-68287" limsid="24-68287"/>
        <qc-flag>UNKNOWN</qc-flag>
        <location>
            <container uri="http://web-claritytest-01.internal.sanger.ac.uk:8080/api/v2/containers/27-14426" limsid="27-14426"/>
            <value>G:6</value>
        </location>
        <working-flag>true</working-flag>
        <sample uri="http://web-claritytest-01.internal.sanger.ac.uk:8080/api/v2/samples/44Y203A53" limsid="44Y203A53"/>
        <workflow-stages/>
    </art:artifact>
    <art:artifact uri="http://web-claritytest-01.internal.sanger.ac.uk:8080/api/v2/artifacts/2-411225?state=210453" limsid="2-411225">
        <name>Fluidigm Analysis File</name>
        <type>Analyte</type>
        <output-type>Analyte</output-type>
        <parent-process uri="http://web-claritytest-01.internal.sanger.ac.uk:8080/api/v2/processes/24-68287" limsid="24-68287"/>
        <qc-flag>UNKNOWN</qc-flag>
        <location>
            <container uri="http://web-claritytest-01.internal.sanger.ac.uk:8080/api/v2/containers/27-14426" limsid="27-14426"/>
            <value>C:5</value>
        </location>
        <working-flag>true</working-flag>
        <sample uri="http://web-claritytest-01.internal.sanger.ac.uk:8080/api/v2/samples/44Y203A52" limsid="44Y203A52"/>
        <workflow-stages/>
    </art:artifact>
    <art:artifact uri="http://web-claritytest-01.internal.sanger.ac.uk:8080/api/v2/artifacts/2-411226?state=210454" limsid="2-411226">
        <name>Fluidigm Analysis File</name>
        <type>Analyte</type>
        <output-type>Analyte</output-type>
        <parent-process uri="http://web-claritytest-01.internal.sanger.ac.uk:8080/api/v2/processes/24-68287" limsid="24-68287"/>
        <qc-flag>UNKNOWN</qc-flag>
        <location>
            <container uri="http://web-claritytest-01.internal.sanger.ac.uk:8080/api/v2/containers/27-14426" limsid="27-14426"/>
            <value>G:5</value>
        </location>
        <working-flag>true</working-flag>
        <sample uri="http://web-claritytest-01.internal.sanger.ac.uk:8080/api/v2/samples/44Y203A51" limsid="44Y203A51"/>
        <workflow-stages/>
    </art:artifact>
    <art:artifact uri="http://web-claritytest-01.internal.sanger.ac.uk:8080/api/v2/artifacts/2-411227?state=210455" limsid="2-411227">
        <name>Fluidigm Analysis File</name>
        <type>Analyte</type>
        <output-type>Analyte</output-type>
        <parent-process uri="http://web-claritytest-01.internal.sanger.ac.uk:8080/api/v2/processes/24-68287" limsid="24-68287"/>
        <qc-flag>UNKNOWN</qc-flag>
        <location>
            <container uri="http://web-claritytest-01.internal.sanger.ac.uk:8080/api/v2/containers/27-14426" limsid="27-14426"/>
            <value>B:2</value>
        </location>
        <working-flag>true</working-flag>
        <sample uri="http://web-claritytest-01.internal.sanger.ac.uk:8080/api/v2/samples/44Y203A50" limsid="44Y203A50"/>
        <workflow-stages/>
    </art:artifact>
    <art:artifact uri="http://web-claritytest-01.internal.sanger.ac.uk:8080/api/v2/artifacts/2-411228?state=210456" limsid="2-411228">
        <name>Fluidigm Analysis File</name>
        <type>Analyte</type>
        <output-type>Analyte</output-type>
        <parent-process uri="http://web-claritytest-01.internal.sanger.ac.uk:8080/api/v2/processes/24-68287" limsid="24-68287"/>
        <qc-flag>UNKNOWN</qc-flag>
        <location>
            <container uri="http://web-claritytest-01.internal.sanger.ac.uk:8080/api/v2/containers/27-14426" limsid="27-14426"/>
            <value>L:5</value>
        </location>
        <working-flag>true</working-flag>
        <sample uri="http://web-claritytest-01.internal.sanger.ac.uk:8080/api/v2/samples/3C-402" limsid="3C-402"/>
        <control-type uri="http://web-claritytest-01.internal.sanger.ac.uk:8080/api/v2/controltypes/3"/>
        <workflow-stages/>
    </art:artifact>
    <art:artifact uri="http://web-claritytest-01.internal.sanger.ac.uk:8080/api/v2/artifacts/2-411229?state=210457" limsid="2-411229">
        <name>Fluidigm Analysis File</name>
        <type>Analyte</type>
        <output-type>Analyte</output-type>
        <parent-process uri="http://web-claritytest-01.internal.sanger.ac.uk:8080/api/v2/processes/24-68287" limsid="24-68287"/>
        <qc-flag>UNKNOWN</qc-flag>
        <location>
            <container uri="http://web-claritytest-01.internal.sanger.ac.uk:8080/api/v2/containers/27-14426" limsid="27-14426"/>
            <value>P:5</value>
        </location>
        <working-flag>true</working-flag>
        <sample uri="http://web-claritytest-01.internal.sanger.ac.uk:8080/api/v2/samples/3C-405" limsid="3C-405"/>
        <control-type uri="http://web-claritytest-01.internal.sanger.ac.uk:8080/api/v2/controltypes/3"/>
        <workflow-stages/>
    </art:artifact>
    <art:artifact uri="http://web-claritytest-01.internal.sanger.ac.uk:8080/api/v2/artifacts/2-411230?state=210458" limsid="2-411230">
        <name>Fluidigm Analysis File</name>
        <type>Analyte</type>
        <output-type>Analyte</output-type>
        <parent-process uri="http://web-claritytest-01.internal.sanger.ac.uk:8080/api/v2/processes/24-68287" limsid="24-68287"/>
        <qc-flag>UNKNOWN</qc-flag>
        <location>
            <container uri="http://web-claritytest-01.internal.sanger.ac.uk:8080/api/v2/containers/27-14426" limsid="27-14426"/>
            <value>N:5</value>
        </location>
        <working-flag>true</working-flag>
        <sample uri="http://web-claritytest-01.internal.sanger.ac.uk:8080/api/v2/samples/3C-452" limsid="3C-452"/>
        <control-type uri="http://web-claritytest-01.internal.sanger.ac.uk:8080/api/v2/controltypes/3"/>
        <workflow-stages/>
    </art:artifact>
    <art:artifact uri="http://web-claritytest-01.internal.sanger.ac.uk:8080/api/v2/artifacts/2-411231?state=210459" limsid="2-411231">
        <name>Fluidigm Analysis File</name>
        <type>Analyte</type>
        <output-type>Analyte</output-type>
        <parent-process uri="http://web-claritytest-01.internal.sanger.ac.uk:8080/api/v2/processes/24-68287" limsid="24-68287"/>
        <qc-flag>UNKNOWN</qc-flag>
        <location>
            <container uri="http://web-claritytest-01.internal.sanger.ac.uk:8080/api/v2/containers/27-14426" limsid="27-14426"/>
            <value>P:6</value>
        </location>
        <working-flag>true</working-flag>
        <sample uri="http://web-claritytest-01.internal.sanger.ac.uk:8080/api/v2/samples/2C-464" limsid="2C-464"/>
        <control-type uri="http://web-claritytest-01.internal.sanger.ac.uk:8080/api/v2/controltypes/2"/>
        <workflow-stages/>
    </art:artifact>
</art:details>